vsc/__init__.py
vsc/__main__.py
vsc/attrs.py
vsc/constraints.py
vsc/coverage.py
vsc/methods.py
vsc/rand_obj.py
vsc/types.py
py_vsc-0.0.1.20200326.3.dist-info/LICENSE
py_vsc-0.0.1.20200326.3.dist-info/METADATA
py_vsc-0.0.1.20200326.3.dist-info/WHEEL
py_vsc-0.0.1.20200326.3.dist-info/entry_points.txt
py_vsc-0.0.1.20200326.3.dist-info/top_level.txt
py_vsc-0.0.1.20200326.3.dist-info/RECORD
