Metadata-Version: 2.1
Name: py-vsc
Version: 0.0.1.20200326.3
Summary: py-vsc (Verification Stimulus and Coverage) is a Python package for generating randomized stimulus and defining and collecting functional coverage.
Home-page: https://github.com/fvutils/py-vsc
Author: Matthew Ballance
Author-email: matt.ballance@gmail.com
License: Apache 2.0
Keywords: Python,Functional Verification,Constraints,Coverage
Platform: UNKNOWN
Requires-Dist: pyboolector
